{"openapi":"3.1.0","info":{"title":"LegalTech AI Service","description":"AI and NLP pipelines for contract analysis","version":"1.0.0"},"paths":{"/api/v1/chat":{"post":{"summary":"Chat","operationId":"chat_api_v1_chat_post","requestBody":{"content":{"application/json":{"schema":{"$ref":"#/components/schemas/ChatRequest"}}},"required":true},"responses":{"200":{"description":"Successful Response","content":{"application/json":{"schema":{}}}},"422":{"description":"Validation Error","content":{"application/json":{"schema":{"$ref":"#/components/schemas/HTTPValidationError"}}}}}}},"/translate":{"post":{"summary":"Translate","operationId":"translate_translate_post","requestBody":{"content":{"application/json":{"schema":{"$ref":"#/components/schemas/TranslateRequest"}}},"required":true},"responses":{"200":{"description":"Successful Response","content":{"application/json":{"schema":{}}}},"422":{"description":"Validation Error","content":{"application/json":{"schema":{"$ref":"#/components/schemas/HTTPValidationError"}}}}}}},"/health":{"get":{"summary":"Health Check","operationId":"health_check_health_get","responses":{"200":{"description":"Successful Response","content":{"application/json":{"schema":{}}}}}}},"/":{"get":{"summary":"Root","operationId":"root__get","responses":{"200":{"description":"Successful Response","content":{"application/json":{"schema":{}}}}}}}},"components":{"schemas":{"ChatRequest":{"properties":{"contract_id":{"type":"string","title":"Contract Id"},"question":{"type":"string","title":"Question"}},"type":"object","required":["contract_id","question"],"title":"ChatRequest"},"HTTPValidationError":{"properties":{"detail":{"items":{"$ref":"#/components/schemas/ValidationError"},"type":"array","title":"Detail"}},"type":"object","title":"HTTPValidationError"},"TranslateRequest":{"properties":{"text":{"type":"string","title":"Text"},"target_language":{"type":"string","title":"Target Language","default":"en"}},"type":"object","required":["text"],"title":"TranslateRequest"},"ValidationError":{"properties":{"loc":{"items":{"anyOf":[{"type":"string"},{"type":"integer"}]},"type":"array","title":"Location"},"msg":{"type":"string","title":"Message"},"type":{"type":"string","title":"Error Type"}},"type":"object","required":["loc","msg","type"],"title":"ValidationError"}}}}